l2winddir/__init__.py
l2winddir/data_module.py
l2winddir/loss.py
l2winddir/main.py
l2winddir/predict.py
l2winddir/simple_conv.py
l2winddir-0.0.3.dist-info/METADATA
l2winddir-0.0.3.dist-info/WHEEL
l2winddir-0.0.3.dist-info/top_level.txt
l2winddir-0.0.3.dist-info/RECORD
