Metadata-Version: 2.1
Name: l2winddir
Version: 0.0.3
Summary: A package for l2 wind direction
Author: jean2262
Author-email: jrenaud495@gmail.com
Classifier: Programming Language :: Python :: 3
Classifier: License :: OSI Approved :: MIT License
Classifier: Operating System :: OS Independent
Requires-Python: >=3.11
Requires-Dist: hydra-core
Requires-Dist: hydra-zen
Requires-Dist: pandas
Requires-Dist: xarray
Requires-Dist: numpy
Requires-Dist: lightning
Requires-Dist: omegaconf
Requires-Dist: tqdm
Requires-Dist: einops
